{
    "targets": [
        {
            "type": "Location",
            "channels": [
                "Facebook",
                "Linkedin",
                "Twitter",
                "Instagram",
                "Google AdWords"
             ]
        },
        {
            "type": "Age",
            "channels":[
                "Facebook",
                "Linkedin",
                "Twitter",
                "Instagram",
                "Google AdWords"
             ]
        },
        {
            "type": "Sex",
            "channels":[
                "Facebook",
                "Linkedin",
                "Twitter",
                "Instagram",
                "Google AdWords"
             ]
        },
        {
            "type": "Spoken languages",
            "channels":[
                "Facebook",
                "Twitter",
                "Instagram"
             ]
        },
        {
            "type": "Events",
            "channels":[
                "Facebook",
                "Twitter"
             ]
        },
        {
            "type": "Company",
            "channels":[
                "Linkedin"
             ]
        },
        {
            "type": "Industry",
            "channels":[
                "Linkedin",
                "SEO"
             ]
        },
        {
            "type": "Expertise",
            "channels":[
                "Linkedin"
             ]
        },
        {
            "type": "Education",
            "channels":[
                "Linkedin"
             ]
        },
        {
            "type": "Technology",
            "channels":[
                "Twitter"
             ]
        },
        {
            "type": "Interests",
            "channels":[
                "Instagram"
             ]
        },
        {
            "type": "Device",
            "channels":[
                "Google AdWords"
             ]
        },
        {
            "type": "Keywords",
            "channels":[
                "Google AdWords",
                "SEO"
             ]
        },
        {
            "type": "Similar products / services",
            "channels":[
                "Google AdWords"
             ]
        },
        {
            "type": "Hyperlinks",
            "channels":[
                "SEO"
             ]
        }
    ]
}
